{
  "info": {
    "name": "Institution Bank Account API",
    "description": "Complete API collection for testing Institution Bank Account endpoints",
    "schema": "https://schema.getpostman.com/json/collection/v2.1.0/collection.json"
  },
  "variable": [
    {
      "key": "base_url",
      "value": "http://localhost:8000",
      "type": "string"
    },
    {
      "key": "auth_token",
      "value": "",
      "type": "string"
    },
    {
      "key": "username",
      "value": "admin",
      "type": "string"
    },
    {
      "key": "password",
      "value": "admin_password",
      "type": "string"
    },
    {
      "key": "institution_id",
      "value": "",
      "type": "string"
    },
    {
      "key": "institution_entity_id",
      "value": "",
      "type": "string"
    },
    {
      "key": "bank_account_id",
      "value": "",
      "type": "string"
    },
    {
      "key": "address_id",
      "value": "",
      "type": "string"
    }
  ],
  "auth": {
    "type": "bearer",
    "bearer": [
      {
        "key": "token",
        "value": "{{auth_token}}",
        "type": "string"
      }
    ]
  },
  "event": [
    {
      "listen": "prerequest",
      "script": {
        "exec": [
          "// Set default headers",
          "pm.request.headers.add({",
          "    key: 'Content-Type',",
          "    value: 'application/json'",
          "});",
          "",
          "// Handle authentication: skip for login, add bearer token for others",
          "const requestUrl = pm.request.url.toString();",
          "const isLoginRequest = requestUrl.includes('/auth/token');",
          "const authToken = pm.collectionVariables.get('auth_token');",
          "",
          "if (!isLoginRequest && authToken && authToken.trim() !== '') {",
          "    pm.request.headers.remove('Authorization');",
          "    pm.request.headers.add({",
          "        key: 'Authorization',",
          "        value: 'Bearer ' + authToken",
          "    });",
          "} else if (isLoginRequest) {",
          "    pm.request.headers.remove('Authorization');",
          "}"
        ],
        "type": "text/javascript"
      }
    },
    {
      "listen": "test",
      "script": {
        "exec": [
          "// Conditional test - only for successful responses",
          "if (pm.response.code >= 200 && pm.response.code < 300) {",
          "    pm.test('Response has JSON content', function () {",
          "        pm.response.to.have.jsonBody();",
          "    });",
          "}"
        ],
        "type": "text/javascript"
      }
    }
  ],
  "item": [
    {
      "name": "0. Login",
      "request": {
        "method": "POST",
        "header": [
          {
            "key": "Content-Type",
            "value": "application/x-www-form-urlencoded"
          }
        ],
        "body": {
          "mode": "urlencoded",
          "urlencoded": [
            {
              "key": "username",
              "value": "{{username}}"
            },
            {
              "key": "password",
              "value": "{{password}}"
            }
          ]
        },
        "url": {
          "raw": "{{base_url}}/api/v1/auth/token",
          "host": ["{{base_url}}"],
          "path": ["api", "v1", "auth", "token"]
        }
      },
      "event": [
        {
          "listen": "test",
          "script": {
            "exec": [
              "pm.test('Login Successful', function () {",
              "    pm.expect(pm.response.code).to.equal(200);",
              "    const response = pm.response.json();",
              "    pm.expect(response).to.have.property('access_token');",
              "    ",
              "    // Store the auth token for subsequent requests",
              "    pm.collectionVariables.set('auth_token', response.access_token);",
              "    console.log('✅ Login successful. Token stored.');",
              "});"
            ],
            "type": "text/javascript"
          }
        }
      ]
    },
    {
      "name": "1. Create Institution",
      "request": {
        "method": "POST",
        "header": [],
        "body": {
          "mode": "raw",
          "raw": "{\n  \"name\": \"Test Institution\"\n}",
          "options": {
            "raw": {
              "language": "json"
            }
          }
        },
        "url": {
          "raw": "{{base_url}}/api/v1/institutions/",
          "host": ["{{base_url}}"],
          "path": ["api", "v1", "institutions", ""]
        }
      },
      "event": [
        {
          "listen": "test",
          "script": {
            "exec": [
              "pm.test('Institution Created Successfully', function () {",
              "    pm.expect(pm.response.code).to.equal(201);",
              "    const response = pm.response.json();",
              "    pm.expect(response).to.have.property('institution_id');",
              "    ",
              "    pm.collectionVariables.set('institution_id', response.institution_id);",
              "    console.log('Created Institution ID:', response.institution_id);",
              "});"
            ],
            "type": "text/javascript"
          }
        }
      ]
    },
    {
      "name": "2. Create Address",
      "request": {
        "method": "POST",
        "header": [],
        "body": {
          "mode": "raw",
          "raw": "{\n  \"institution_id\": \"{{institution_id}}\",\n  \"user_id\": \"11111111-1111-1111-1111-111111111111\",\n  \"address_type\": [\"Entity Address\"],\n  \"country_code\": \"ARG\",\n  \"province\": \"Buenos Aires\",\n  \"city\": \"Buenos Aires\",\n  \"postal_code\": \"1000\",\n  \"street_type\": \"Street\",\n  \"street_name\": \"Test Street\",\n  \"building_number\": \"123\"\n}",
          "options": {
            "raw": {
              "language": "json"
            }
          }
        },
        "url": {
          "raw": "{{base_url}}/api/v1/addresses/",
          "host": ["{{base_url}}"],
          "path": ["api", "v1", "addresses", ""]
        }
      },
      "event": [
        {
          "listen": "test",
          "script": {
            "exec": [
              "pm.test('Address Created Successfully', function () {",
              "    pm.expect(pm.response.code).to.equal(201);",
              "    const response = pm.response.json();",
              "    pm.expect(response).to.have.property('address_id');",
              "    ",
              "    pm.collectionVariables.set('address_id', response.address_id);",
              "    console.log('Created Address ID:', response.address_id);",
              "});"
            ],
            "type": "text/javascript"
          }
        }
      ]
    },
    {
      "name": "3. Create Institution Entity",
      "request": {
        "method": "POST",
        "header": [],
        "body": {
          "mode": "raw",
          "raw": "{\n  \"institution_id\": \"{{institution_id}}\",\n  \"address_id\": \"{{address_id}}\",\n  \"tax_id\": \"TAX123456789\",\n  \"name\": \"Test Institution Entity\"\n}",
          "options": {
            "raw": {
              "language": "json"
            }
          }
        },
        "url": {
          "raw": "{{base_url}}/api/v1/institution-entities/",
          "host": ["{{base_url}}"],
          "path": ["api", "v1", "institution-entities", ""]
        }
      },
      "event": [
        {
          "listen": "test",
          "script": {
            "exec": [
              "pm.test('Institution Entity Created Successfully', function () {",
              "    pm.expect(pm.response.code).to.equal(201);",
              "    const response = pm.response.json();",
              "    pm.expect(response).to.have.property('institution_entity_id');",
              "    ",
              "    pm.collectionVariables.set('institution_entity_id', response.institution_entity_id);",
              "    console.log('Created Institution Entity ID:', response.institution_entity_id);",
              "});"
            ],
            "type": "text/javascript"
          }
        }
      ]
    },
    {
      "name": "4. Create Bank Account (Full)",
      "request": {
        "method": "POST",
        "header": [],
        "body": {
          "mode": "raw",
          "raw": "{\n  \"institution_entity_id\": \"{{institution_entity_id}}\",\n  \"address_id\": \"{{address_id}}\",\n  \"account_holder_name\": \"John Doe\",\n  \"bank_name\": \"Chase Bank\",\n  \"account_type\": \"Checking\",\n  \"routing_number\": \"021000021\",\n  \"account_number\": \"1234567890\",\n  \"status\": \"Active\"\n}",
          "options": {
            "raw": {
              "language": "json"
            }
          }
        },
        "url": {
          "raw": "{{base_url}}/api/v1/institution-bank-accounts/",
          "host": ["{{base_url}}"],
          "path": ["api", "v1", "institution-bank-accounts", ""]
        }
      },
      "event": [
        {
          "listen": "test",
          "script": {
            "exec": [
              "pm.test('Bank Account Created Successfully', function () {",
              "    pm.expect(pm.response.code).to.equal(201);",
              "    const response = pm.response.json();",
              "    pm.expect(response).to.have.property('bank_account_id');",
              "    pm.expect(response).to.have.property('account_holder_name');",
              "    pm.expect(response).to.have.property('bank_name');",
              "    ",
              "    // Store the bank_account_id for later use",
              "    pm.collectionVariables.set('bank_account_id', response.bank_account_id);",
              "    ",
              "    console.log('Created Bank Account ID:', response.bank_account_id);",
              "});"
            ],
            "type": "text/javascript"
          }
        }
      ]
    },
    {
      "name": "5. Create Bank Account (Minimal)",
      "request": {
        "method": "POST",
        "header": [],
        "body": {
          "mode": "raw",
          "raw": "{\n  \"institution_entity_id\": \"{{institution_entity_id}}\",\n  \"account_holder_name\": \"Jane Smith\",\n  \"bank_name\": \"Bank of America\",\n  \"account_type\": \"Savings\",\n  \"routing_number\": \"026009593\",\n  \"account_number\": \"9876543210\"\n}",
          "options": {
            "raw": {
              "language": "json"
            }
          }
        },
        "url": {
          "raw": "{{base_url}}/api/v1/institution-bank-accounts/minimal",
          "host": ["{{base_url}}"],
          "path": ["api", "v1", "institution-bank-accounts", "minimal"]
        }
      },
      "event": [
        {
          "listen": "test",
          "script": {
            "exec": [
              "pm.test('Minimal Bank Account Created Successfully', function () {",
              "    pm.expect(pm.response.code).to.equal(201);",
              "    const response = pm.response.json();",
              "    pm.expect(response).to.have.property('bank_account_id');",
              "    pm.expect(response).to.have.property('address_id');",
              "    pm.expect(response).to.have.property('status');",
              "    pm.expect(response.status).to.equal('Active');",
              "    ",
              "    // Store the bank_account_id for later use",
              "    pm.collectionVariables.set('bank_account_id', response.bank_account_id);",
              "    ",
              "    console.log('Created Minimal Bank Account ID:', response.bank_account_id);",
              "    console.log('Auto-populated Address ID:', response.address_id);",
              "});"
            ],
            "type": "text/javascript"
          }
        }
      ]
    },
    {
      "name": "6. Get Bank Account by ID",
      "request": {
        "method": "GET",
        "header": [],
        "url": {
          "raw": "{{base_url}}/api/v1/institution-bank-accounts/{{bank_account_id}}",
          "host": ["{{base_url}}"],
          "path": ["api", "v1", "institution-bank-accounts", "{{bank_account_id}}"]
        }
      },
      "event": [
        {
          "listen": "test",
          "script": {
            "exec": [
              "pm.test('Bank Account Retrieved Successfully', function () {",
              "    pm.expect(pm.response.code).to.equal(200);",
              "    const response = pm.response.json();",
              "    pm.expect(response.bank_account_id).to.equal(pm.collectionVariables.get('bank_account_id'));",
              "    pm.expect(response.account_holder_name).to.equal('John Doe');",
              "    pm.expect(response.bank_name).to.equal('Chase Bank');",
              "    ",
              "    console.log('Retrieved Bank Account:', response.account_holder_name, 'at', response.bank_name);",
              "});"
            ],
            "type": "text/javascript"
          }
        }
      ]
    },
    {
      "name": "7. Get All Bank Accounts",
      "request": {
        "method": "GET",
        "header": [],
        "url": {
          "raw": "{{base_url}}/api/v1/institution-bank-accounts/",
          "host": ["{{base_url}}"],
          "path": ["api", "v1", "institution-bank-accounts", ""]
        }
      },
      "event": [
        {
          "listen": "test",
          "script": {
            "exec": [
              "pm.test('All Bank Accounts Retrieved Successfully', function () {",
              "    pm.expect(pm.response.code).to.equal(200);",
              "    const response = pm.response.json();",
              "    pm.expect(response).to.be.an('array');",
              "    pm.expect(response.length).to.be.greaterThan(0);",
              "    ",
              "    console.log('Total Bank Accounts:', response.length);",
              "    response.forEach((account, index) => {",
              "        console.log(`${index + 1}. ${account.account_holder_name} - ${account.bank_name}`);",
              "    });",
              "});"
            ],
            "type": "text/javascript"
          }
        }
      ]
    },
    {
      "name": "8. Get Bank Accounts by Institution Entity",
      "request": {
        "method": "GET",
        "header": [],
        "url": {
          "raw": "{{base_url}}/api/v1/institution-bank-accounts/?institution_entity_id={{institution_entity_id}}",
          "host": ["{{base_url}}"],
          "path": ["api", "v1", "institution-bank-accounts", ""],
          "query": [
            {
              "key": "institution_entity_id",
              "value": "{{institution_entity_id}}"
            }
          ]
        }
      },
      "event": [
        {
          "listen": "test",
          "script": {
            "exec": [
              "pm.test('Bank Accounts by Institution Entity Retrieved Successfully', function () {",
              "    pm.expect(pm.response.code).to.equal(200);",
              "    const response = pm.response.json();",
              "    pm.expect(response).to.be.an('array');",
              "    ",
              "    // All accounts should belong to the same institution entity",
              "    response.forEach(account => {",
              "        pm.expect(account.institution_entity_id).to.equal(pm.collectionVariables.get('institution_entity_id'));",
              "    });",
              "    ",
              "    console.log('Bank Accounts for Institution Entity:', response.length);",
              "});"
            ],
            "type": "text/javascript"
          }
        }
      ]
    },
    {
      "name": "9. Get Active Bank Accounts",
      "request": {
        "method": "GET",
        "header": [],
        "url": {
          "raw": "{{base_url}}/api/v1/institution-bank-accounts/active/{{institution_entity_id}}",
          "host": ["{{base_url}}"],
          "path": ["api", "v1", "institution-bank-accounts", "active", "{{institution_entity_id}}"]
        }
      },
      "event": [
        {
          "listen": "test",
          "script": {
            "exec": [
              "pm.test('Active Bank Accounts Retrieved Successfully', function () {",
              "    pm.expect(pm.response.code).to.equal(200);",
              "    const response = pm.response.json();",
              "    pm.expect(response).to.be.an('array');",
              "    ",
              "    // All accounts should be active",
              "    response.forEach(account => {",
              "        pm.expect(account.status).to.equal('Active');",
              "        pm.expect(account.is_archived).to.equal(false);",
              "    });",
              "    ",
              "    console.log('Active Bank Accounts:', response.length);",
              "});"
            ],
            "type": "text/javascript"
          }
        }
      ]
    },
    {
      "name": "10. Update Bank Account",
      "request": {
        "method": "PUT",
        "header": [],
        "body": {
          "mode": "raw",
          "raw": "{\n  \"account_holder_name\": \"John Doe Updated\",\n  \"status\": \"Inactive\"\n}",
          "options": {
            "raw": {
              "language": "json"
            }
          }
        },
        "url": {
          "raw": "{{base_url}}/api/v1/institution-bank-accounts/{{bank_account_id}}",
          "host": ["{{base_url}}"],
          "path": ["api", "v1", "institution-bank-accounts", "{{bank_account_id}}"]
        }
      },
      "event": [
        {
          "listen": "test",
          "script": {
            "exec": [
              "pm.test('Bank Account Updated Successfully', function () {",
              "    pm.expect(pm.response.code).to.equal(200);",
              "    const response = pm.response.json();",
              "    pm.expect(response.account_holder_name).to.equal('John Doe Updated');",
              "    pm.expect(response.status).to.equal('Inactive');",
              "    ",
              "    console.log('Updated Bank Account:', response.account_holder_name, 'Status:', response.status);",
              "});"
            ],
            "type": "text/javascript"
          }
        }
      ]
    },
    {
      "name": "11. Validate Bank Account",
      "request": {
        "method": "POST",
        "header": [],
        "url": {
          "raw": "{{base_url}}/api/v1/institution-bank-accounts/{{bank_account_id}}/validate",
          "host": ["{{base_url}}"],
          "path": ["api", "v1", "institution-bank-accounts", "{{bank_account_id}}", "validate"]
        }
      },
      "event": [
        {
          "listen": "test",
          "script": {
            "exec": [
              "pm.test('Bank Account Validation Successful', function () {",
              "    pm.expect(pm.response.code).to.equal(200);",
              "    const response = pm.response.json();",
              "    pm.expect(response).to.have.property('routing_number_valid');",
              "    pm.expect(response).to.have.property('account_number_valid');",
              "    pm.expect(response).to.have.property('overall_valid');",
              "    ",
              "    console.log('Validation Result:', response);",
              "    ",
              "    if (response.overall_valid) {",
              "        console.log('✅ Bank account validation passed');",
              "    } else {",
              "        console.log('❌ Bank account validation failed:', response.validation_notes);",
              "    }",
              "});"
            ],
            "type": "text/javascript"
          }
        }
      ]
    },
    {
      "name": "12. Invalid Routing Number (Too Short)",
          "request": {
            "method": "POST",
            "header": [],
            "body": {
              "mode": "raw",
              "raw": "{\n  \"institution_entity_id\": \"{{institution_entity_id}}\",\n  \"address_id\": \"{{address_id}}\",\n  \"account_holder_name\": \"Test User\",\n  \"bank_name\": \"Test Bank\",\n  \"account_type\": \"Checking\",\n  \"routing_number\": \"12345\",\n  \"account_number\": \"1234567890\"\n}",
              "options": {
                "raw": {
                  "language": "json"
                }
              }
            },
            "url": {
              "raw": "{{base_url}}/api/v1/institution-bank-accounts/",
              "host": ["{{base_url}}"],
              "path": ["api", "v1", "institution-bank-accounts", ""]
            }
          },
          "event": [
            {
              "listen": "test",
              "script": {
                "exec": [
                  "pm.test('Invalid Routing Number Rejected', function () {",
                  "    pm.expect(pm.response.code).to.equal(422);",
                  "    const response = pm.response.json();",
                  "    pm.expect(response.detail[0].msg).to.include('Invalid routing number format');",
                  "    ",
                  "    console.log('✅ Validation error caught:', response.detail[0].msg);",
                  "});"
                ],
                "type": "text/javascript"
              }
            }
          ]
    },
    {
      "name": "13. Invalid Account Number (Too Short)",
          "request": {
            "method": "POST",
            "header": [],
            "body": {
              "mode": "raw",
              "raw": "{\n  \"institution_entity_id\": \"{{institution_entity_id}}\",\n  \"address_id\": \"{{address_id}}\",\n  \"account_holder_name\": \"Test User\",\n  \"bank_name\": \"Test Bank\",\n  \"account_type\": \"Checking\",\n  \"routing_number\": \"123456789\",\n  \"account_number\": \"123\"\n}",
              "options": {
                "raw": {
                  "language": "json"
                }
              }
            },
            "url": {
              "raw": "{{base_url}}/api/v1/institution-bank-accounts/",
              "host": ["{{base_url}}"],
              "path": ["api", "v1", "institution-bank-accounts", ""]
            }
          },
          "event": [
            {
              "listen": "test",
              "script": {
                "exec": [
                  "pm.test('Invalid Account Number Rejected', function () {",
                  "    pm.expect(pm.response.code).to.equal(422);",
                  "    const response = pm.response.json();",
                  "    pm.expect(response.detail[0].msg).to.include('Invalid account number format');",
                  "    ",
                  "    console.log('✅ Validation error caught:', response.detail[0].msg);",
                  "});"
                ],
                "type": "text/javascript"
              }
            }
          ]
    },
    {
      "name": "14. Invalid Account Type",
          "request": {
            "method": "POST",
            "header": [],
            "body": {
              "mode": "raw",
              "raw": "{\n  \"institution_entity_id\": \"{{institution_entity_id}}\",\n  \"address_id\": \"{{address_id}}\",\n  \"account_holder_name\": \"Test User\",\n  \"bank_name\": \"Test Bank\",\n  \"account_type\": \"InvalidType\",\n  \"routing_number\": \"123456789\",\n  \"account_number\": \"1234567890\"\n}",
              "options": {
                "raw": {
                  "language": "json"
                }
              }
            },
            "url": {
              "raw": "{{base_url}}/api/v1/institution-bank-accounts/",
              "host": ["{{base_url}}"],
              "path": ["api", "v1", "institution-bank-accounts", ""]
            }
          },
          "event": [
            {
              "listen": "test",
              "script": {
                "exec": [
                  "pm.test('Invalid Account Type Rejected', function () {",
                  "    pm.expect(pm.response.code).to.equal(422);",
                  "    const response = pm.response.json();",
                  "    pm.expect(response.detail[0].msg).to.include('Invalid account type');",
                  "    ",
                  "    console.log('✅ Validation error caught:', response.detail[0].msg);",
                  "});"
                ],
                "type": "text/javascript"
              }
            }
          ]
    },
    {
      "name": "15. Delete Bank Account",
      "request": {
        "method": "DELETE",
        "header": [],
        "url": {
          "raw": "{{base_url}}/api/v1/institution-bank-accounts/{{bank_account_id}}",
          "host": ["{{base_url}}"],
          "path": ["api", "v1", "institution-bank-accounts", "{{bank_account_id}}"]
        }
      },
      "event": [
        {
          "listen": "test",
          "script": {
            "exec": [
              "pm.test('Bank Account Deleted Successfully', function () {",
              "    pm.expect(pm.response.code).to.equal(200);",
              "    const response = pm.response.json();",
              "    pm.expect(response.detail).to.equal('Bank account deleted successfully');",
              "    ",
              "    console.log('✅ Bank account deleted:', response.detail);",
              "});"
            ],
            "type": "text/javascript"
          }
        }
      ]
    },
    {
      "name": "16. Verify Deletion",
      "request": {
        "method": "GET",
        "header": [],
        "url": {
          "raw": "{{base_url}}/api/v1/institution-bank-accounts/{{bank_account_id}}",
          "host": ["{{base_url}}"],
          "path": ["api", "v1", "institution-bank-accounts", "{{bank_account_id}}"]
        }
      },
      "event": [
        {
          "listen": "test",
          "script": {
            "exec": [
              "pm.test('Bank Account Not Found After Deletion', function () {",
              "    pm.expect(pm.response.code).to.equal(404);",
              "    const response = pm.response.json();",
              "    pm.expect(response.detail).to.equal('Bank account not found');",
              "    ",
              "    console.log('✅ Bank account not found after deletion (soft delete working)');",
              "});"
            ],
            "type": "text/javascript"
          }
        }
      ]
    }
  ]
}